MaidaPy/ListTools.py
MaidaPy/RotateArray.py
MaidaPy/__init__.py
MaidaPy-0.0.1.dist-info/LICENSE.txt
MaidaPy-0.0.1.dist-info/METADATA
MaidaPy-0.0.1.dist-info/WHEEL
MaidaPy-0.0.1.dist-info/top_level.txt
MaidaPy-0.0.1.dist-info/RECORD
