Metadata-Version: 2.1
Name: MaidaPy
Version: 0.0.1
Summary: My first Library
Home-page: UNKNOWN
Author: Maida
License: UNKNOWN
Platform: UNKNOWN
License-File: LICENSE.txt
